{
  "results": [
    {
      "id": "1128291022340059364",
      "title": "",
      "content_description": "a drawing of a desk with a laptop and the words self rules",
      "content_rating": "",
      "h1_title": "",
      "media": [
        {
          "nanowebm": {
            "preview": "https://media.tenor.com/D6h-tPXXcOQAAAAg/self-roles.png",
            "url": "https://media.tenor.com/D6h-tPXXcOQAAAP4/self-roles.webm",
            "duration": 1.2,
            "dims": [
              150,
              112
            ],
            "size": 9872
          },
          "tinywebm": {
            "duration": 1.2,
            "url": "https://media.tenor.com/D6h-tPXXcOQAAAP3/self-roles.webm",
            "dims": [
              320,
              238
            ],
            "preview": "https://media.tenor.com/D6h-tPXXcOQAAAAf/self-roles.png",
            "size": 28769
          },
          "tinygif": {
            "size": 30268,
            "duration": 1.2,
            "url": "https://media.tenor.com/D6h-tPXXcOQAAAAM/self-roles.gif",
            "dims": [
              220,
              164
            ],
            "preview": "https://media.tenor.com/D6h-tPXXcOQAAAAN/self-roles.png"
          },
          "mp4": {
            "preview": "https://media.tenor.com/D6h-tPXXcOQAAAAD/self-roles.png",
            "duration": 1.2,
            "url": "https://media.tenor.com/D6h-tPXXcOQAAAPo/self-roles.mp4",
            "dims": [
              640,
              478
            ],
            "size": 229349
          },
          "nanogif": {
            "duration": 1.2,
            "url": "https://media.tenor.com/D6h-tPXXcOQAAAAS/self-roles.gif",
            "dims": [
              121,
              90
            ],
            "preview": "https://media.tenor.com/D6h-tPXXcOQAAAAT/self-roles.png",
            "size": 11187
          },
          "tinymp4": {
            "dims": [
              320,
              238
            ],
            "duration": 1.2,
            "url": "https://media.tenor.com/D6h-tPXXcOQAAAP1/self-roles.mp4",
            "preview": "https://media.tenor.com/D6h-tPXXcOQAAAAf/self-roles.png",
            "size": 46229
          },
          "webp_transparent": {
            "preview": "https://media.tenor.com/D6h-tPXXcOQAAAAt/self-roles.webp",
            "duration": 1.2,
            "url": "https://media.tenor.com/D6h-tPXXcOQAAAAl/self-roles.webp",
            "dims": [
              498,
              373
            ],
            "size": 137258
          },
          "nanowebp_transparent": {
            "size": 3388,
            "preview": "https://media.tenor.com/D6h-tPXXcOQAAAAv/self-roles.webp",
            "duration": 1.2,
            "url": "https://media.tenor.com/D6h-tPXXcOQAAAAn/self-roles.webp",
            "dims": [
              90,
              68
            ]
          },
          "webp": {
            "size": 67050,
            "preview": "https://media.tenor.com/D6h-tPXXcOQAAAAD/self-roles.png",
            "duration": 1.2,
            "url": "https://media.tenor.com/D6h-tPXXcOQAAAAx/self-roles.webp",
            "dims": [
              498,
              372
            ]
          },
          "gif": {
            "size": 742897,
            "url": "https://media.tenor.com/D6h-tPXXcOQAAAAC/self-roles.gif",
            "duration": 1.2,
            "dims": [
              498,
              371
            ],
            "preview": "https://media.tenor.com/D6h-tPXXcOQAAAAD/self-roles.png"
          },
          "nanomp4": {
            "size": 13373,
            "preview": "https://media.tenor.com/D6h-tPXXcOQAAAAg/self-roles.png",
            "duration": 1.2,
            "url": "https://media.tenor.com/D6h-tPXXcOQAAAP2/self-roles.mp4",
            "dims": [
              150,
              112
            ]
          },
          "loopedmp4": {
            "size": 686530,
            "dims": [
              640,
              478
            ],
            "duration": 3.6,
            "url": "https://media.tenor.com/D6h-tPXXcOQAAAPw/self-roles.mp4",
            "preview": "https://media.tenor.com/D6h-tPXXcOQAAAAD/self-roles.png"
          },
          "webm": {
            "duration": 1.2,
            "url": "https://media.tenor.com/D6h-tPXXcOQAAAPs/self-roles.webm",
            "dims": [
              640,
              478
            ],
            "preview": "https://media.tenor.com/D6h-tPXXcOQAAAAD/self-roles.png",
            "size": 37216
          },
          "mediumgif": {
            "url": "https://media.tenor.com/D6h-tPXXcOQAAAAd/self-roles.gif",
            "duration": 1.2,
            "dims": [
              640,
              478
            ],
            "preview": "https://media.tenor.com/D6h-tPXXcOQAAAAe/self-roles.png",
            "size": 252903
          },
          "tinywebp_transparent": {
            "size": 15550,
            "duration": 1.2,
            "url": "https://media.tenor.com/D6h-tPXXcOQAAAAm/self-roles.webp",
            "dims": [
              200,
              150
            ],
            "preview": "https://media.tenor.com/D6h-tPXXcOQAAAAu/self-roles.webp"
          }
        }
      ],
      "bg_color": "",
      "created": 1650393442.967303,
      "itemurl": "https://tenor.com/view/self-roles-gif-25437956",
      "url": "https://tenor.com/bSTJM.gif",
      "tags": [],
      "flags": [],
      "shares": 1,
      "hasaudio": false,
      "hascaption": false,
      "source_id": "",
      "composite": null
    },
    {
      "id": "12801003319309722298",
      "title": "",
      "content_description": "a drawing of a laptop with a flower on the screen and the letters ehv-e on the bottom right",
      "content_rating": "",
      "h1_title": "",
      "media": [
        {
          "mp4": {
            "size": 153224,
            "preview": "https://media.tenor.com/saZMskANYroAAAAD/notebook-pc.png",
            "dims": [
              640,
              480
            ],
            "duration": 1.2,
            "url": "https://media.tenor.com/saZMskANYroAAAPo/notebook-pc.mp4"
          },
          "nanogif": {
            "size": 11123,
            "preview": "https://media.tenor.com/saZMskANYroAAAAT/notebook-pc.png",
            "url": "https://media.tenor.com/saZMskANYroAAAAS/notebook-pc.gif",
            "duration": 1.2,
            "dims": [
              120,
              90
            ]
          },
          "tinymp4": {
            "size": 43540,
            "duration": 1.2,
            "url": "https://media.tenor.com/saZMskANYroAAAP1/notebook-pc.mp4",
            "dims": [
              320,
              240
            ],
            "preview": "https://media.tenor.com/saZMskANYroAAAAf/notebook-pc.png"
          },
          "webp_transparent": {
            "url": "https://media.tenor.com/saZMskANYroAAAAl/notebook-pc.webp",
            "duration": 1.2,
            "dims": [
              498,
              374
            ],
            "preview": "https://media.tenor.com/saZMskANYroAAAAt/notebook-pc.webp",
            "size": 75738
          },
          "nanowebm": {
            "size": 9428,
            "preview": "https://media.tenor.com/saZMskANYroAAAAg/notebook-pc.png",
            "url": "https://media.tenor.com/saZMskANYroAAAP4/notebook-pc.webm",
            "duration": 1.2,
            "dims": [
              150,
              112
            ]
          },
          "tinywebm": {
            "size": 27538,
            "dims": [
              320,
              240
            ],
            "duration": 1.2,
            "url": "https://media.tenor.com/saZMskANYroAAAP3/notebook-pc.webm",
            "preview": "https://media.tenor.com/saZMskANYroAAAAf/notebook-pc.png"
          },
          "tinygif": {
            "preview": "https://media.tenor.com/saZMskANYroAAAAN/notebook-pc.png",
            "duration": 1.2,
            "url": "https://media.tenor.com/saZMskANYroAAAAM/notebook-pc.gif",
            "dims": [
              220,
              165
            ],
            "size": 29783
          },
          "gif": {
            "size": 719937,
            "preview": "https://media.tenor.com/saZMskANYroAAAAD/notebook-pc.png",
            "duration": 1.2,
            "url": "https://media.tenor.com/saZMskANYroAAAAC/notebook-pc.gif",
            "dims": [
              498,
              373
            ]
          },
          "webp": {
            "preview": "https://media.tenor.com/saZMskANYroAAAAD/notebook-pc.png",
            "duration": 1.2,
            "url": "https://media.tenor.com/saZMskANYroAAAAx/notebook-pc.webp",
            "dims": [
              498,
              374
            ],
            "size": 55668
          },
          "loopedmp4": {
            "size": 458155,
            "preview": "https://media.tenor.com/saZMskANYroAAAAD/notebook-pc.png",
            "url": "https://media.tenor.com/saZMskANYroAAAPw/notebook-pc.mp4",
            "duration": 3.6,
            "dims": [
              640,
              480
            ]
          },
          "nanomp4": {
            "duration": 1.2,
            "url": "https://media.tenor.com/saZMskANYroAAAP2/notebook-pc.mp4",
            "dims": [
              150,
              112
            ],
            "preview": "https://media.tenor.com/saZMskANYroAAAAg/notebook-pc.png",
            "size": 12766
          },
          "mediumgif": {
            "duration": 1.2,
            "url": "https://media.tenor.com/saZMskANYroAAAAd/notebook-pc.gif",
            "dims": [
              640,
              480
            ],
            "preview": "https://media.tenor.com/saZMskANYroAAAAe/notebook-pc.png",
            "size": 200277
          },
          "tinywebp_transparent": {
            "preview": "https://media.tenor.com/saZMskANYroAAAAu/notebook-pc.webp",
            "duration": 1.2,
            "url": "https://media.tenor.com/saZMskANYroAAAAm/notebook-pc.webp",
            "dims": [
              200,
              150
            ],
            "size": 16404
          },
          "webm": {
            "size": 46120,
            "dims": [
              640,
              480
            ],
            "duration": 1.2,
            "url": "https://media.tenor.com/saZMskANYroAAAPs/notebook-pc.webm",
            "preview": "https://media.tenor.com/saZMskANYroAAAAD/notebook-pc.png"
          },
          "nanowebp_transparent": {
            "size": 3700,
            "url": "https://media.tenor.com/saZMskANYroAAAAn/notebook-pc.webp",
            "duration": 1.2,
            "dims": [
              90,
              68
            ],
            "preview": "https://media.tenor.com/saZMskANYroAAAAv/notebook-pc.webp"
          }
        }
      ],
      "bg_color": "",
      "created": 1586371178.063741,
      "itemurl": "https://tenor.com/view/notebook-pc-laptop-work-pink-gif-16825020",
      "url": "https://tenor.com/biK7s.gif",
      "tags": [],
      "flags": [],
      "shares": 1,
      "hasaudio": false,
      "hascaption": false,
      "source_id": "",
      "composite": null
    },
    {
      "id": "3461007565604184012",
      "title": "",
      "content_description": "a drawing of a desk with a laptop and a cup of coffee",
      "content_rating": "",
      "h1_title": "",
      "media": [
        {
          "nanowebp_transparent": {
            "size": 18142,
            "dims": [
              90,
              68
            ],
            "duration": 6,
            "url": "https://media.tenor.com/MAf4CzDG38wAAAAn/divine-aesthetic.webp",
            "preview": "https://media.tenor.com/MAf4CzDG38wAAAAv/divine-aesthetic.webp"
          },
          "nanomp4": {
            "size": 24789,
            "dims": [
              108,
              80
            ],
            "duration": 6,
            "url": "https://media.tenor.com/MAf4CzDG38wAAAP2/divine-aesthetic.mp4",
            "preview": "https://media.tenor.com/MAf4CzDG38wAAAAg/divine-aesthetic.png"
          },
          "loopedmp4": {
            "duration": 18,
            "url": "https://media.tenor.com/MAf4CzDG38wAAAPw/divine-aesthetic.mp4",
            "dims": [
              640,
              478
            ],
            "preview": "https://media.tenor.com/MAf4CzDG38wAAAAD/divine-aesthetic.png",
            "size": 1809401
          },
          "gif": {
            "size": 7302733,
            "preview": "https://media.tenor.com/MAf4CzDG38wAAAAD/divine-aesthetic.png",
            "duration": 6,
            "url": "https://media.tenor.com/MAf4CzDG38wAAAAC/divine-aesthetic.gif",
            "dims": [
              498,
              371
            ]
          },
          "webp": {
            "preview": "https://media.tenor.com/MAf4CzDG38wAAAAD/divine-aesthetic.png",
            "duration": 6,
            "url": "https://media.tenor.com/MAf4CzDG38wAAAAx/divine-aesthetic.webp",
            "dims": [
              498,
              372
            ],
            "size": 327658
          },
          "mediumgif": {
            "duration": 6,
            "url": "https://media.tenor.com/MAf4CzDG38wAAAAd/divine-aesthetic.gif",
            "dims": [
              640,
              478
            ],
            "preview": "https://media.tenor.com/MAf4CzDG38wAAAAe/divine-aesthetic.png",
            "size": 613230
          },
          "tinywebp_transparent": {
            "preview": "https://media.tenor.com/MAf4CzDG38wAAAAu/divine-aesthetic.webp",
            "duration": 6,
            "url": "https://media.tenor.com/MAf4CzDG38wAAAAm/divine-aesthetic.webp",
            "dims": [
              200,
              150
            ],
            "size": 124300
          },
          "webm": {
            "url": "https://media.tenor.com/MAf4CzDG38wAAAPs/divine-aesthetic.webm",
            "duration": 6,
            "dims": [
              640,
              478
            ],
            "preview": "https://media.tenor.com/MAf4CzDG38wAAAAD/divine-aesthetic.png",
            "size": 155140
          },
          "nanowebm": {
            "preview": "https://media.tenor.com/MAf4CzDG38wAAAAg/divine-aesthetic.png",
            "url": "https://media.tenor.com/MAf4CzDG38wAAAP4/divine-aesthetic.webm",
            "duration": 6,
            "dims": [
              108,
              80
            ],
            "size": 16368
          },
          "tinywebm": {
            "duration": 6,
            "url": "https://media.tenor.com/MAf4CzDG38wAAAP3/divine-aesthetic.webm",
            "dims": [
              208,
              154
            ],
            "preview": "https://media.tenor.com/MAf4CzDG38wAAAAf/divine-aesthetic.png",
            "size": 45554
          },
          "tinygif": {
            "size": 67815,
            "duration": 6,
            "url": "https://media.tenor.com/MAf4CzDG38wAAAAM/divine-aesthetic.gif",
            "dims": [
              220,
              164
            ],
            "preview": "https://media.tenor.com/MAf4CzDG38wAAAAN/divine-aesthetic.png"
          },
          "nanogif": {
            "size": 27668,
            "preview": "https://media.tenor.com/MAf4CzDG38wAAAAT/divine-aesthetic.png",
            "duration": 6,
            "url": "https://media.tenor.com/MAf4CzDG38wAAAAS/divine-aesthetic.gif",
            "dims": [
              121,
              90
            ]
          },
          "tinymp4": {
            "size": 71495,
            "duration": 6,
            "url": "https://media.tenor.com/MAf4CzDG38wAAAP1/divine-aesthetic.mp4",
            "dims": [
              208,
              154
            ],
            "preview": "https://media.tenor.com/MAf4CzDG38wAAAAf/divine-aesthetic.png"
          },
          "webp_transparent": {
            "size": 520242,
            "duration": 6,
            "url": "https://media.tenor.com/MAf4CzDG38wAAAAl/divine-aesthetic.webp",
            "dims": [
              364,
              273
            ],
            "preview": "https://media.tenor.com/MAf4CzDG38wAAAAt/divine-aesthetic.webp"
          },
          "mp4": {
            "preview": "https://media.tenor.com/MAf4CzDG38wAAAAD/divine-aesthetic.png",
            "dims": [
              640,
              478
            ],
            "duration": 6,
            "url": "https://media.tenor.com/MAf4CzDG38wAAAPo/divine-aesthetic.mp4",
            "size": 603634
          }
        }
      ],
      "bg_color": "",
      "created": 1593503155.2509511,
      "itemurl": "https://tenor.com/view/divine-aesthetic-laptop-mood-pink-gif-17665426",
      "url": "https://tenor.com/bmhKo.gif",
      "tags": [],
      "flags": [],
      "shares": 1,
      "hasaudio": false,
      "hascaption": false,
      "source_id": "",
      "composite": null
    }
  ],
  "next": "3"
}
